cocolit/__init__.py
cocolit/data.py
cocolit/defaults.py
cocolit/gradacc.py
cocolit/networks.py
cocolit/sampling.py
cocolit/utils.py
cocolit/wisl.py
cocolit/cli/mri2pet.py
cocolit-0.2.1.dist-info/licenses/LICENSE
cocolit-0.2.1.dist-info/METADATA
cocolit-0.2.1.dist-info/WHEEL
cocolit-0.2.1.dist-info/entry_points.txt
cocolit-0.2.1.dist-info/top_level.txt
cocolit-0.2.1.dist-info/RECORD
