Metadata-Version: 2.4
Name: cocolit
Version: 0.2.1
Summary: CoCoLIT: ControlNet-Conditioned Latent Image Translation for MRI to Amyloid PET Synthesis
Author-email: Lemuel Puglisi <lemuelpuglisi001@gmail.com>, Alec Sargood <alec.sargood.23@ucl.ac.uk>
Classifier: Programming Language :: Python :: 3
Classifier: License :: OSI Approved :: MIT License
Classifier: Operating System :: OS Independent
Requires-Python: >=3.9
License-File: LICENSE
Requires-Dist: torch<3.0,>=2.0
Requires-Dist: monai<2.0,>=1.0
Requires-Dist: monai-generative<0.3,>=0.2
Requires-Dist: huggingface_hub
Requires-Dist: matplotlib
Requires-Dist: nibabel
Requires-Dist: numpy
Requires-Dist: pandas
Requires-Dist: rich
Requires-Dist: PyYAML
Requires-Dist: tqdm
Requires-Dist: wandb
Requires-Dist: scipy
Dynamic: license-file
